facebook_event_aggregator/Event.py
facebook_event_aggregator/__main__.py
facebook_event_aggregator/repo.py
facebook_event_aggregator/export/__init__.py
facebook_event_aggregator/export/to_html.py
facebook_event_aggregator/export/to_ics.py
facebook_event_aggregator/export/utils.py
facebook_event_aggregator/export/templates/workaround.py
facebook_event_aggregator/scraper/__init__.py
facebook_event_aggregator/scraper/driver.py
facebook_event_aggregator/scraper/fb_login.py
facebook_event_aggregator/scraper/scrape_all.py
facebook_event_aggregator/scraper/scrape_event_page.py
facebook_event_aggregator/scraper/scrape_events_page.py
facebook_event_aggregator/scraper/utils.py
facebook_event_aggregator/utils/fb_regexes.py
facebook_event_aggregator/utils/url_converter.py
tests/__init__.py
tests/test_Event.py
tests/test_repo.py
tests/export/__init__.py
tests/export/helpers.py
tests/export/test_export_html.py
tests/export/test_export_ics.py
tests/export/test_utils.py
tests/scraper/test_scrape.py
tests/utils/__init__.py
tests/utils/test_fb_regexes.py
tests/utils/test_url_converter.py
facebook_event_aggregator-0.2.0.dist-info/LICENSE
facebook_event_aggregator-0.2.0.dist-info/METADATA
facebook_event_aggregator-0.2.0.dist-info/WHEEL
facebook_event_aggregator-0.2.0.dist-info/entry_points.txt
facebook_event_aggregator-0.2.0.dist-info/top_level.txt
facebook_event_aggregator-0.2.0.dist-info/RECORD
