Metadata-Version: 2.1
Name: facebook-event-aggregator
Version: 0.2.0
Author-email: Denperidge <denperidge@gmail.com>
Project-URL: Homepage, https://github.com/Denperidge/facebook-event-aggregator
Project-URL: Bug Tracker, https://github.com/Denperidge/facebook-event-aggregator/issues
Classifier: Development Status :: 4 - Beta
Classifier: Environment :: Console
Requires-Python: >=3.10
License-File: LICENSE
Requires-Dist: python-slugify >=7.0.0
Requires-Dist: python-dateutil >=2.8.2
Requires-Dist: gitpython >=3.1.40
Requires-Dist: webdriver-manager >=4.0.1
Requires-Dist: selenium >=4.15.2
Requires-Dist: ics >=0.7.2
Requires-Dist: Jinja2 >=3.1.2
